TokenProbs/__init__.py
TokenProbs/logit_extraction-old.py
TokenProbs/logit_extraction.py
TokenProbs-1.0.3.dist-info/LICENSE
TokenProbs-1.0.3.dist-info/METADATA
TokenProbs-1.0.3.dist-info/WHEEL
TokenProbs-1.0.3.dist-info/top_level.txt
TokenProbs-1.0.3.dist-info/RECORD
