Metadata-Version: 2.1
Name: TokenProbs
Version: 1.0.3
Summary: Extract token-level probabilities from LLMs for classification-type outputs.
Author: Francesco A. Fabozzi
Author-email: francescoafabozzi@gmail.com
Keywords: python,LLMs,finance,forecasting,language models,huggingface
Classifier: Development Status :: 1 - Planning
Classifier: Programming Language :: Python :: 3
Classifier: Programming Language :: Python :: 3.8
Classifier: Programming Language :: Python :: 3.9
Classifier: Programming Language :: Python :: 3.10
Classifier: Programming Language :: Python :: 3.11
Classifier: Programming Language :: Python :: 3.12
Requires-Python: >=3.8,<3.13
License-File: LICENSE
Requires-Dist: transformers >=4.0.0
Requires-Dist: bitsandbytes
Requires-Dist: datasets
Requires-Dist: accelerate
Requires-Dist: loralib
Requires-Dist: peft
Requires-Dist: trl
Requires-Dist: torch
Requires-Dist: tqdm
Requires-Dist: pandas
